skore_local_project/__init__.py
skore_local_project/metadata.py
skore_local_project/project.py
skore_local_project/storage.py
skore_local_project-0.0.5.dist-info/METADATA
skore_local_project-0.0.5.dist-info/WHEEL
skore_local_project-0.0.5.dist-info/entry_points.txt
skore_local_project-0.0.5.dist-info/licenses/LICENSE
skore_local_project-0.0.5.dist-info/RECORD
