Metadata-Version: 2.4
Name: skore-local-project
Version: 0.0.5
Maintainer-email: skore developers <skore@signal.probabl.ai>
License-Expression: MIT
License-File: LICENSE
Requires-Python: >=3.10
Requires-Dist: diskcache
Requires-Dist: joblib
Requires-Dist: platformdirs
Requires-Dist: rich
Provides-Extra: test
Requires-Dist: pandas; extra == 'test'
Requires-Dist: pre-commit; extra == 'test'
Requires-Dist: pytest; extra == 'test'
Requires-Dist: pytest-cov; extra == 'test'
Requires-Dist: pytest-order; extra == 'test'
Requires-Dist: pytest-randomly; extra == 'test'
Requires-Dist: pytest-xdist; extra == 'test'
Requires-Dist: skore; extra == 'test'
Requires-Dist: xdoctest; extra == 'test'
